{"chunk_definitions":[{"row":11,"row_count":1,"visible":true,"expansion_state":0,"options":{"engine":"r","label":"setup","include":false},"document_id":"F4366500","chunk_id":"csetup_chunk","chunk_label":"setup"},{"row":43,"row_count":1,"visible":true,"expansion_state":0,"options":{"engine":"r","label":"unnamed-chunk-50"},"document_id":"F4366500","chunk_id":"c9vxag2dzoasu","chunk_label":"unnamed-chunk-4"},{"row":152,"row_count":1,"visible":true,"expansion_state":0,"options":{"engine":"r","label":"unnamed-chunk-108"},"document_id":"F4366500","chunk_id":"cckkaxr094rzu","chunk_label":"unnamed-chunk-16"},{"row":260,"row_count":1,"visible":true,"expansion_state":0,"options":{"engine":"r","label":"unnamed-chunk-139"},"document_id":"F4366500","chunk_id":"c085ij129czwg","chunk_label":"unnamed-chunk-27"}],"doc_write_time":1640351050,"working_dir":null,"default_chunk_options":{"echo":true}}